Workbook

Sheet How to Use
B2: ARC Collections Intelligence — Feature Checklist
B3: Companion to Tekion_ARC_Collections_PRD_v1.1.docx · Use this to scope and approve the Phase 1 release.
B5: Purpose
B6: This workbook lists every feature described in the PRD (v1.1), grouped by module. For each feature it shows the PRD's suggested rollout phase, a rough effort size, an overall priority, and a recommended Phase 1 call. You make the final decision in the 'P1 Decision' column, then use the 'Phase 1 Summary' tab to see what has been approved.
B11: How to use it
B12: 1. Open the 'Feature Checklist' tab. Each row is one feature. Use the column filters (row 1) to sort by Module, Phase, or Recommendation.
B13: 2. Review the 'P1 Recommended' column (my suggested Phase 1 scope): Yes = ship in Phase 1, Consider = optional / partial, No = later phase.
B14: 3. Record your decision in the 'P1 Decision' column using the dropdown (Approved for Phase 1 / Deferred / Out of scope / Needs discussion).
B15: 4. Fill 'Owner' and 'Notes' as needed. The 'Phase 1 Summary' tab updates automatically from your decisions.
B17: Column guide
B18: Ref | C18: PRD section reference for the feature.
B19: Module | C19: Which of the six product modules the feature belongs to.
B20: Origin | C20: 'v1.0' = in the original PRD · 'New v1.1' = added in the expansion · 'Exists today' = already live in the current platform.
B21: PRD Phase | C21: Rollout phase suggested by the PRD (Section 9). Phase 4 items are the long-term horizon.
B22: Effort | C22: Rough build size — S (small) / M (medium) / L (large). Directional, not an estimate.
B23: Priority | C23: Overall product priority: Must / Should / Could.
B24: P1 Recommended | C24: My suggested Phase 1 scope: Yes / Consider / No.
B25: P1 Decision | C25: YOUR call — the editable column. Dropdown provided.
B26: Dependencies | C26: What the feature needs before it can ship.
B28: Editable columns are shaded yellow in the checklist. Example — set 'P1 Decision' to 'Approved for Phase 1' for the core collections features, then check the summary tab.
B31: Excluded from this scope (tracked separately)
B32: • Disputes — no system-driven dispute flow (customer raise / dealership acknowledge) exists today; handled as a separate task. • Customer chat / messaging — treated as a separate task, same as disputes. The business portal (invoice view + payment via gateway) already exists and is marked 'Exists today' in the checklist.

Sheet Feature Checklist
A1: Ref | B1: Module | C1: Feature | D1: Description | E1: Origin | F1: PRD Phase | G1: Effort | H1: Priority | I1: P1 Recommended | J1: P1 Decision | K1: Dependencies | L1: Owner | M1: Notes
A2: 4A.1 | B2: M1 · Collections Engine | C2: AI-ranked collector workqueue | D2: Daily ranked worklist; P1–P6 priority tiers; system-recommended action per invoice. | E2: v1.0 | F2: Phase 1 | G2: M | H2: Must | I2: Yes | J2: TBD | K2: Invoice sync; priority scoring
A3: 4A.1 | B3: M1 · Collections Engine | C3: Priority scoring engine (rule-based) | D3: Scores by days-past-due, amount, contact recency, and broken-PTP history. | E3: v1.0 | F3: Phase 1 | G3: M | H3: Must | I3: Yes | J3: TBD | K3: Invoice + payment history
A4: 4A.2 | B4: M1 · Collections Engine | C4: Automated dunning sequences (email) | D4: Configurable multi-step reminder sequences triggered by invoice aging. | E4: v1.0 | F4: Phase 1 | G4: L | H4: Must | I4: Yes | J4: TBD | K4: Email delivery; templates
A5: 4A.2 | B5: M1 · Collections Engine | C5: Dunning suppression rules | D5: Auto-pause sequences on active PTP, offer-in-checkout, or VIP flag. | E5: v1.0 | F5: Phase 1 | G5: M | H5: Must | I5: Yes | J5: TBD | K5: PTP module
A6: 4A.4 | B6: M1 · Collections Engine | C6: Promise-to-pay tracker | D6: Capture PTPs; suppress dunning; broken-PTP alerts; installment PTPs. | E6: v1.0 | F6: Phase 1 | G6: M | H6: Must | I6: Yes | J6: TBD | K6: Workqueue
A7: 4A.5 | B7: M1 · Collections Engine | C7: Cash application — auto-match | D7: Auto-apply payments matching amount + customer + date; post to ARC GL. | E7: v1.0 | F7: Phase 1 | G7: M | H7: Must | I7: Yes | J7: TBD | K7: ARC write-back
A8: 4A.5 | B8: M1 · Collections Engine | C8: Cash application — remittance OCR / short-pay | D8: OCR remittance parsing; short-pay exceptions; unapplied-cash queue. | E8: v1.0 | F8: Phase 2 | G8: L | H8: Should | I8: No | J8: TBD | K8: OCR service
A9: 4A.6 | B9: M1 · Collections Engine | C9: Deductions & short-pay management | D9: Identify short-pays where a buyer pays less than invoiced; AI valid/invalid coding; recovery task or auto write-off. | E9: New v1.1 | F9: Phase 3 | G9: M | H9: Should | I9: No | J9: TBD | K9: Cash application
A10: 4A.7 | B10: M1 · Collections Engine | C10: Late fees, interest & finance charges | D10: Configurable charge rules; grace/waivers; scheduled assessment; posts to ARC. | E10: New v1.1 | F10: Phase 3 | G10: M | H10: Could | I10: No | J10: TBD | K10: Compliance (disclosures)
A11: 4A.8 | B11: M1 · Collections Engine | C11: Payment plans & structured arrangements | D11: Multi-installment plans; auto-scheduling; broken-plan escalation; ACH auto-pay. | E11: New v1.1 | F11: Phase 2 | G11: M | H11: Should | I11: Consider | J11: TBD | K11: PTP; payment gateway
A12: 4A.9 | B12: M1 · Collections Engine | C12: Escalation, write-off, agency & legal | D12: Escalation ladder; write-off approvals; agency placement; legal referral. | E12: New v1.1 | F12: Phase 3 | G12: M | H12: Should | I12: Consider | J12: TBD | K12: Approvals; ARC GL
A13: 4A.10 | B13: M1 · Collections Engine | C13: Customer statements & invoice presentment | D13: Periodic + consolidated statements; portal retrieval; delivery tracking. | E13: New v1.1 | F13: Phase 2 | G13: M | H13: Should | I13: Consider | J13: TBD | K13: Statement generation | M13: Customers can already view invoices in the business portal; net-new = periodic + consolidated statements.
A14: 4A.11 | B14: M1 · Collections Engine | C14: Omnichannel communication (SMS/WhatsApp/portal/phone) | D14: Beyond email: SMS, WhatsApp, portal notifications, and call talking points for outbound reminders (one-way). | E14: New v1.1 | F14: Phase 2 | G14: L | H14: Should | I14: No | J14: TBD | K14: Consent (M5); channel providers
A15: 4B.1 | B15: M2 · Early Payment Network | C15: Early payment discount engine (fixed + sliding) | D15: Time-limited discount offers; fixed % and sliding-scale models. | E15: v1.0 | F15: Phase 2 | G15: L | H15: Should | I15: No | J15: TBD | K15: Portal + gateway already live | M15: Portal + payment gateway already exist, lowering build risk.
A16: 4B.1 | B16: M2 · Early Payment Network | C16: AI-recommended discount | D16: Calculates minimum discount likely to trigger acceptance per invoice/buyer. | E16: v1.0 | F16: Phase 3 | G16: L | H16: Could | I16: No | J16: TBD | K16: Payment DNA (ML)
A17: 4B.2 | B17: M2 · Early Payment Network | C17: Customer Payment DNA grading (rule-based) | D17: Grade accounts Easy→Risky from payment history; feeds workqueue + eligibility. | E17: v1.0 | F17: Phase 1 | G17: M | H17: Should | I17: Consider | J17: TBD | K17: Payment history
A18: 4B.2 | B18: M2 · Early Payment Network | C18: Customer Payment DNA grading (ML model) | D18: Machine-learned behavioural grading and payment-cycle detection. | E18: v1.0 | F18: Phase 3 | G18: L | H18: Could | I18: No | J18: TBD | K18: Cross-dealer data; ML platform
A19: 4B.3 | B19: M2 · Early Payment Network | C19: Smart liquidity offers (targeted) | D19: AI shortlist of reliable high-balance buyers for targeted discounts; enforced eligibility. | E19: v1.0 | F19: Phase 3 | G19: L | H19: Could | I19: No | J19: TBD | K19: Payment DNA; offers engine
A20: 4B.1 | B20: M2 · Early Payment Network | C20: Early-payment offer layer on business portal | D20: Offer dashboard, savings calculator, and multi-invoice discount checkout ON TOP OF the existing business portal. | E20: v1.0 | F20: Phase 2 | G20: M | H20: Should | I20: No | J20: TBD | K20: Base portal already live | M20: Base business portal already live; this row is only the early-payment discount layer on top of it.
A21: 4B.- | B21: M2 · Early Payment Network | C21: Campaign management (bulk offers) | D21: CFO sets blanket discount across eligible invoices for a date range. | E21: v1.0 | F21: Phase 2 | G21: M | H21: Should | I21: No | J21: TBD | K21: Offers engine
A22: 5.- | B22: M2 · Early Payment Network | C22: Business portal — invoice view + payment gateway | D22: Customers view invoices and pay via the payment gateway. | E22: Exists today | F22: Live | G22: - | H22: Must | I22: Yes | J22: TBD | K22: Already in place | M22: Already LIVE in the current platform — no build. Prerequisite for the early-payment layer.
A23: 4C.1 | B23: M3 · Credit Management | C23: Credit application & onboarding | D23: Digital credit app; bureau checks; AI decisioning; terms + limit assignment. | E23: New v1.1 | F23: Phase 3 | G23: L | H23: Could | I23: No | J23: TBD | K23: Bureau integration
A24: 4C.2 | B24: M3 · Credit Management | C24: Credit scoring & limit setting | D24: Blended internal+external score; limit recommendation; live exposure view. | E24: New v1.1 | F24: Phase 3 | G24: L | H24: Could | I24: No | J24: TBD | K24: Bureau; payment history
A25: 4C.3 | B25: M3 · Credit Management | C25: Ongoing credit review & credit holds | D25: Periodic re-review; dynamic holds; early-warning signals; blocks new orders in ARC. | E25: New v1.1 | F25: Phase 3 | G25: M | H25: Could | I25: No | J25: TBD | K25: ARC order block
A26: 4D.1 | B26: M4 · AI Intelligence Layer | C26: AI Collection Command Center / Daily Brief | D26: AI daily brief; smart clickable KPIs; priority worklist; health score. | E26: New v1.1 | F26: Phase 2 | G26: M | H26: Should | I26: Consider | J26: TBD | K26: Risk engine (prototype exists)
A27: 4D.2 | B27: M4 · AI Intelligence Layer | C27: AI Copilot (conversational) | D27: Chat assistant over live AR data; summary+evidence+confidence+next action. | E27: New v1.1 | F27: Phase 3 | G27: L | H27: Could | I27: No | J27: TBD | K27: Tekion AI platform | M27: Internal collector assistant, not customer-facing chat. Confirm scope.
A28: 4D.3 | B28: M4 · AI Intelligence Layer | C28: Explainable risk engine (rule-based, top-3 factors) | D28: Every score shows its top-3 plain-language drivers. | E28: New v1.1 | F28: Phase 1 | G28: M | H28: Should | I28: Yes | J28: TBD | K28: Priority scoring
A29: 4D.3 | B29: M4 · AI Intelligence Layer | C29: Explainable risk engine (ML) | D29: Learned scoring with feedback loop from collector outcomes. | E29: New v1.1 | F29: Phase 3 | G29: L | H29: Could | I29: No | J29: TBD | K29: ML platform
A30: 4D.4 | B30: M4 · AI Intelligence Layer | C30: Predictive insights (default / broken-PTP / cash) | D30: Default probability; broken-promise prediction; cash + DSO forecast; future aging. | E30: New v1.1 | F30: Phase 3 | G30: L | H30: Could | I30: No | J30: TBD | K30: ML platform; history
A31: 4D.5 | B31: M4 · AI Intelligence Layer | C31: Intelligent communication strategy | D31: AI tone + channel selection with stated rationale; outcome prediction. | E31: New v1.1 | F31: Phase 3 | G31: M | H31: Could | I31: No | J31: TBD | K31: Omnichannel; risk engine
A32: 4E.1 | B32: M5 · Compliance & Audit | C32: Communication compliance & consent | D32: Per-channel consent; opt-out/STOP; frequency caps; quiet hours; disclosures. | E32: New v1.1 | F32: Phase 1 | G32: M | H32: Must | I32: Yes | J32: TBD | K32: Any automated outreach
A33: 4E.2 | B33: M5 · Compliance & Audit | C33: Audit trail & data governance | D33: Immutable action log; stored AI rationale; role-based access; export. | E33: New v1.1 | F33: Phase 1 | G33: M | H33: Must | I33: Yes | J33: TBD | K33: All modules
A34: 4F.1 | B34: M6 · Collector Management | C34: Collector capacity & workload balancing | D34: Per-collector load view; assignment rules; rebalancing; SLA monitoring. | E34: New v1.1 | F34: Phase 3 | G34: M | H34: Could | I34: No | J34: TBD | K34: Multi-collector dealers
A35: 4F.2 | B35: M6 · Collector Management | C35: Collector performance & coaching | D35: Recovery-outcome metrics; coaching signals; optional leaderboard; group roll-up. | E35: New v1.1 | F35: Phase 3 | G35: M | H35: Could | I35: No | J35: TBD | K35: Workload data
A36: 5.1 | B36: Platform & Integration | C36: ARC Accounting invoice sync (bidirectional) | D36: Live read of invoices, terms, aging, payment history; status write-back. | E36: v1.0 | F36: Phase 1 | G36: L | H36: Must | I36: Yes | J36: TBD | K36: ARC Accounting
A37: 5.1 | B37: Platform & Integration | C37: ARC write-back (payments, cash app, GL, credit notes) | D37: Post payment settlement, discounts, and cash application to ARC GL. | E37: v1.0 | F37: Phase 1 | G37: M | H37: Must | I37: Yes | J37: TBD | K37: ARC Accounting
A38: 5.1 | B38: Platform & Integration | C38: ARC Service read (RO / parts context) | D38: Read RO and parts context to enrich account and invoice detail. | E38: v1.0 | F38: Phase 2 | G38: M | H38: Should | I38: Consider | J38: TBD | K38: ARC Service
A39: 5.1 | B39: Platform & Integration | C39: ARC CRM read/write (contacts, activity logs) | D39: Read contact info; write collection activity logs and task completions. | E39: v1.0 | F39: Phase 1 | G39: M | H39: Should | I39: Yes | J39: TBD | K39: ARC CRM
... A52: 9 | B52: Platform & Integration | C52: API for third-party factoring integration | D52: Open API for external factoring partners. | E52: v1.0 | F52: Phase 4 | G52: M | H52: Could | I52: No | J52: TBD | K52: Partner APIs

Sheet Phase 1 Summary
B2: Phase 1 Scope — Live Summary
B3: Counts update automatically from the 'P1 Decision' and 'P1 Recommended' columns in the checklist.
B5: Total features in scope | D5: =COUNTA('Feature Checklist'!$C$2:$C$52) -> 51
B7: By my Phase 1 recommendation
B8: Yes (ship in Phase 1) | D8: =COUNTIF('Feature Checklist'!$I$2:$I$52,"Yes") -> 17
B9: Consider (optional/partial) | D9: =COUNTIF('Feature Checklist'!$I$2:$I$52,"Consider") -> 7
B10: No (later phase) | D10: =COUNTIF('Feature Checklist'!$I$2:$I$52,"No") -> 27
B12: By your Phase 1 decision
B13: Approved for Phase 1 | D13: =COUNTIF('Feature Checklist'!$J$2:$J$52,"Approved for Phase 1") -> 0
B14: Deferred to later phase | D14: =COUNTIF('Feature Checklist'!$J$2:$J$52,"Deferred to later phase") -> 0
B15: Out of scope | D15: =COUNTIF('Feature Checklist'!$J$2:$J$52,"Out of scope") -> 0
B16: Needs discussion | D16: =COUNTIF('Feature Checklist'!$J$2:$J$52,"Needs discussion") -> 0
B17: TBD | D17: =COUNTIF('Feature Checklist'!$J$2:$J$52,"TBD") -> 51
B19: Approved features by module
B20: Module | C20: In scope | D20: Approved for P1
B21: M1 · Collections Engine | C21: =COUNTIF('Feature Checklist'!$B$2:$B$52,"M1 · Collections Engine") -> 13 | D21: =COUNTIFS('Feature Checklist'!$B$2:$B$52,"M1 · Collections Engine",'Feature Checklist'!$J$2:$J$52,"Approved for Phase 1") -> 0
B22: M2 · Early Payment Network | C22: =COUNTIF('Feature Checklist'!$B$2:$B$52,"M2 · Early Payment Network") -> 8 | D22: =COUNTIFS('Feature Checklist'!$B$2:$B$52,"M2 · Early Payment Network",'Feature Checklist'!$J$2:$J$52,"Approved for Phase 1") -> 0
B23: M3 · Credit Management | C23: =COUNTIF('Feature Checklist'!$B$2:$B$52,"M3 · Credit Management") -> 3 | D23: =COUNTIFS('Feature Checklist'!$B$2:$B$52,"M3 · Credit Management",'Feature Checklist'!$J$2:$J$52,"Approved for Phase 1") -> 0
B24: M4 · AI Intelligence Layer | C24: =COUNTIF('Feature Checklist'!$B$2:$B$52,"M4 · AI Intelligence Layer") -> 7 | D24: =COUNTIFS('Feature Checklist'!$B$2:$B$52,"M4 · AI Intelligence Layer",'Feature Checklist'!$J$2:$J$52,"Approved for Phase 1") -> 0
B25: M5 · Compliance & Audit | C25: =COUNTIF('Feature Checklist'!$B$2:$B$52,"M5 · Compliance & Audit") -> 2 | D25: =COUNTIFS('Feature Checklist'!$B$2:$B$52,"M5 · Compliance & Audit",'Feature Checklist'!$J$2:$J$52,"Approved for Phase 1") -> 0
B26: M6 · Collector Management | C26: =COUNTIF('Feature Checklist'!$B$2:$B$52,"M6 · Collector Management") -> 2 | D26: =COUNTIFS('Feature Checklist'!$B$2:$B$52,"M6 · Collector Management",'Feature Checklist'!$J$2:$J$52,"Approved for Phase 1") -> 0
B27: Platform & Integration | C27: =COUNTIF('Feature Checklist'!$B$2:$B$52,"Platform & Integration") -> 8 | D27: =COUNTIFS('Feature Checklist'!$B$2:$B$52,"Platform & Integration",'Feature Checklist'!$J$2:$J$52,"Approved for Phase 1") -> 0
B28: Analytics & Dashboards | C28: =COUNTIF('Feature Checklist'!$B$2:$B$52,"Analytics & Dashboards") -> 4 | D28: =COUNTIFS('Feature Checklist'!$B$2:$B$52,"Analytics & Dashboards",'Feature Checklist'!$J$2:$J$52,"Approved for Phase 1") -> 0
B29: Commercial & Packaging | C29: =COUNTIF('Feature Checklist'!$B$2:$B$52,"Commercial & Packaging") -> 4 | D29: =COUNTIFS('Feature Checklist'!$B$2:$B$52,"Commercial & Packaging",'Feature Checklist'!$J$2:$J$52,"Approved for Phase 1") -> 0
